Algometrix/__init__.py
Algometrix/algometrix.py
Algometrix/classification_models.py
Algometrix/cross_validation.py
Algometrix/evaluation_metrics.py
Algometrix/problem_types.py
Algometrix/processing_classification.py
Algometrix/processing_regression.py
Algometrix/regression_models.py
Algometrix/validation_classification.py
Algometrix/validation_regression.py
Algometrix-0.0.1.dist-info/LICENSE
Algometrix-0.0.1.dist-info/METADATA
Algometrix-0.0.1.dist-info/WHEEL
Algometrix-0.0.1.dist-info/top_level.txt
Algometrix-0.0.1.dist-info/RECORD
