Metadata-Version: 2.1
Name: Algometrix
Version: 0.0.1
Summary: Algometrix: Your Comprehensive Machine Learning Model Comparison Tool. Easily assess and compare the performance of over 22 classification and 27 regression algorithms across 14 evaluation metrics for both classification and regression problems. Make data-driven decisions to select the best model for your dataset.
Author-email: Rehan Khan <dayel.rehan@gmail.com>
Project-URL: Homepage, https://github.com/ryyhan/Algometrix
Project-URL: Bug Tracker, https://github.com/ryyhan/Algometrix
Classifier: Programming Language :: Python :: 3
Classifier: License :: OSI Approved :: MIT License
Classifier: Operating System :: OS Independent
Requires-Python: >=3.7
License-File: LICENSE
